skbs/__init__.py
skbs/_internal_click_monkey_patches.py
skbs/backend.py
skbs/cli.py
skbs/configutils.py
skbs/pluginutils.py
skbs/default/conf.py
skbs/default/templates/skbs.sft
skbs/default/templates/skbs/plugin.py
skbs/default/templates/skbs/root/_opt._template.plugin.py
skbs/default/templates/skbs/root/_template.root
skbs/default/templates/skbs/root/root/_template.
skbs/pluginutils/__init__.py
skbs/pluginutils/looptools.py
skbs-2.2.1.dist-info/LICENSE.txt
skbs-2.2.1.dist-info/METADATA
skbs-2.2.1.dist-info/WHEEL
skbs-2.2.1.dist-info/entry_points.txt
skbs-2.2.1.dist-info/top_level.txt
skbs-2.2.1.dist-info/RECORD
