Metadata-Version: 2.1
Name: skbs
Version: 2.2.1
Summary: SKeleton BootStrap, a full-powered yet trivial to use and customize template based bootstrap or code generation tool
Home-page: https://github.com/hl037/skbs
Author: Léo Flaventin Hauchecorne
Author-email: hl037.prog@gmail.com
License: GPLv3
Platform: UNKNOWN
Classifier: Development Status :: 6 - Mature
Classifier: Environment :: Console
Classifier: Intended Audience :: Developers
Classifier: License :: OSI Approved :: GNU General Public License v3 (GPLv3)
Classifier: Operating System :: OS Independent
Classifier: Programming Language :: Other Scripting Engines
Classifier: Programming Language :: Python :: 3
Classifier: Topic :: Software Development :: Code Generators
Classifier: Topic :: Text Processing
Classifier: Topic :: Utilities
License-File: LICENSE.txt
Requires-Dist: click (>=0.7)
Requires-Dist: appdirs (>=1.4.4)
Requires-Dist: tempiny (>=1.1)
